spark_bestfit/__init__.py
spark_bestfit/_version.py
spark_bestfit/base_fitter.py
spark_bestfit/collection.py
spark_bestfit/config.py
spark_bestfit/continuous_fitter.py
spark_bestfit/copula.py
spark_bestfit/core.py
spark_bestfit/discrete_fitter.py
spark_bestfit/discrete_fitting.py
spark_bestfit/distributions.py
spark_bestfit/estimation.py
spark_bestfit/fast_ppf.py
spark_bestfit/fitting.py
spark_bestfit/histogram.py
spark_bestfit/metrics.py
spark_bestfit/mixture.py
spark_bestfit/multivariate.py
spark_bestfit/plotting.py
spark_bestfit/progress.py
spark_bestfit/protocols.py
spark_bestfit/results.py
spark_bestfit/sampling.py
spark_bestfit/serialization.py
spark_bestfit/storage.py
spark_bestfit/truncated.py
spark_bestfit/utils.py
spark_bestfit/backends/__init__.py
spark_bestfit/backends/factory.py
spark_bestfit/backends/local.py
spark_bestfit/backends/ray.py
spark_bestfit/backends/spark.py
spark_bestfit-3.0.0.dist-info/METADATA
spark_bestfit-3.0.0.dist-info/WHEEL
spark_bestfit-3.0.0.dist-info/licenses/LICENSE
spark_bestfit-3.0.0.dist-info/RECORD
