Metadata-Version: 2.4
Name: spark-bestfit
Version: 3.0.0
Summary: Modern distribution fitting library with Spark, Ray, and local parallel backends
Project-URL: Documentation, https://spark-bestfit.readthedocs.io/en/latest/
Project-URL: Homepage, https://github.com/dwsmith1983/spark-bestfit
Project-URL: Repository, https://github.com/dwsmith1983/spark-bestfit
Project-URL: Issues, https://github.com/dwsmith1983/spark-bestfit/issues
Author-email: Dustin Smith <dustin.william.smith@gmail.com>
License: MIT
License-File: LICENSE
Keywords: distribution,fitting,pyspark,scipy,spark,statistics
Classifier: Development Status :: 5 - Production/Stable
Classifier: Intended Audience :: Developers
Classifier: Intended Audience :: Science/Research
Classifier: License :: OSI Approved :: MIT License
Classifier: Programming Language :: Python :: 3
Classifier: Programming Language :: Python :: 3.11
Classifier: Programming Language :: Python :: 3.12
Classifier: Programming Language :: Python :: 3.13
Classifier: Topic :: Scientific/Engineering
Classifier: Topic :: Software Development :: Libraries :: Python Modules
Requires-Python: <3.14,>=3.11
Requires-Dist: numpy<3.0.0,>=1.24.0
Requires-Dist: pandas<3.0.0,>=1.5.0
Requires-Dist: scipy<2.0.0,>=1.11.0
Provides-Extra: dev
Requires-Dist: black>=24.10.0; extra == 'dev'
Requires-Dist: hypothesis>=6.100.0; extra == 'dev'
Requires-Dist: isort>=5.13.0; extra == 'dev'
Requires-Dist: matplotlib<4.0.0,>=3.7.0; extra == 'dev'
Requires-Dist: mutmut<3.0.0,>=2.4.0; extra == 'dev'
Requires-Dist: mypy>=1.13.0; extra == 'dev'
Requires-Dist: pandas-stubs>=2.2.0; extra == 'dev'
Requires-Dist: pre-commit>=4.5.0; extra == 'dev'
Requires-Dist: pyarrow<19.0.0,>=12.0.0; extra == 'dev'
Requires-Dist: pyspark<5.0.0,>=3.5.0; extra == 'dev'
Requires-Dist: pytest-benchmark>=5.0.0; extra == 'dev'
Requires-Dist: pytest-cov>=6.0.0; extra == 'dev'
Requires-Dist: pytest-spark>=0.6.0; extra == 'dev'
Requires-Dist: pytest>=8.3.0; extra == 'dev'
Requires-Dist: ray[default]<3.0.0,>=2.9.0; extra == 'dev'
Requires-Dist: ruff>=0.8.0; extra == 'dev'
Requires-Dist: scipy-stubs>=1.14.0; extra == 'dev'
Provides-Extra: docs
Requires-Dist: furo; extra == 'docs'
Requires-Dist: pyarrow<19.0.0,>=12.0.0; extra == 'docs'
Requires-Dist: pyspark<5.0.0,>=3.5.0; extra == 'docs'
Requires-Dist: sphinx-copybutton; extra == 'docs'
Requires-Dist: sphinx>=8.0.0; extra == 'docs'
Provides-Extra: plotting
Requires-Dist: matplotlib<4.0.0,>=3.7.0; extra == 'plotting'
Provides-Extra: ray
Requires-Dist: pyarrow<19.0.0,>=12.0.0; extra == 'ray'
Requires-Dist: ray[default]<3.0.0,>=2.9.0; extra == 'ray'
Provides-Extra: spark
Requires-Dist: pyarrow<19.0.0,>=12.0.0; extra == 'spark'
Requires-Dist: pyspark<5.0.0,>=3.5.0; extra == 'spark'
Provides-Extra: test
Requires-Dist: hypothesis>=6.100.0; extra == 'test'
Requires-Dist: matplotlib<4.0.0,>=3.7.0; extra == 'test'
Requires-Dist: pyarrow<19.0.0,>=12.0.0; extra == 'test'
Requires-Dist: pyspark<5.0.0,>=3.5.0; extra == 'test'
Requires-Dist: pytest-cov>=6.0.0; extra == 'test'
Requires-Dist: pytest-spark>=0.6.0; extra == 'test'
Requires-Dist: pytest>=8.3.0; extra == 'test'
Requires-Dist: ray[default]<3.0.0,>=2.9.0; extra == 'test'
Provides-Extra: test-base
Requires-Dist: hypothesis>=6.100.0; extra == 'test-base'
Requires-Dist: matplotlib<4.0.0,>=3.7.0; extra == 'test-base'
Requires-Dist: pytest-cov>=6.0.0; extra == 'test-base'
Requires-Dist: pytest-spark>=0.6.0; extra == 'test-base'
Requires-Dist: pytest>=8.3.0; extra == 'test-base'
